{"k":"66cd2c1ae7e6f1ed7764057eb1d33912f8f6d63a3059bf7286e26f44d8b32816","v":{"decisions":[{"id":"69e9bd333aa0c479643ab59d","pick":false,"score":0,"reason":"Skip — onsite role conflicts with candidate's preference for remote work."},{"id":"69e9507958811370cb12c9b9","pick":false,"score":0,"reason":"Skip — onsite role conflicts with candidate's preference for remote work."},{"id":"69afa78af63f733065b33beb","pick":false,"score":0,"reason":"Skip — hybrid role conflicts with candidate's preference for remote work."},{"id":"69e8f54a4b0fa35a7076a419","pick":false,"score":0,"reason":"Skip — hybrid role conflicts with candidate's preference for remote work."},{"id":"69e08ddd9564e855a25de3b0","pick":false,"score":0,"reason":"Skip — onsite role conflicts with candidate's preference for remote work."},{"id":"69e8f43f58811370cb1293d7","pick":false,"score":0,"reason":"Skip — onsite role conflicts with candidate's preference for remote work."},{"id":"69e8de3e58811370cb128c6d","pick":false,"score":0,"reason":"Skip — onsite role conflicts with candidate's preference for remote work."},{"id":"69e8f5d64b0fa35a7076a50c","pick":true,"score":80,"reason":"Strong fit — remote Product Manager role with H1B sponsorship, aligns with candidate's seniority and experience."},{"id":"699ff45481476f6176b9d94c","pick":false,"score":55,"reason":"Borderline — senior role but hybrid work model conflicts with candidate's preference for remote work."},{"id":"69e909613aa0c479643a6a09","pick":false,"score":0,"reason":"Skip — remote role but no H1B sponsorship available."},{"id":"699535c481476f6176ad161e","pick":true,"score":75,"reason":"Strong fit — remote Senior Product Manager role with H1B sponsorship, aligns with candidate's seniority and experience."},{"id":"69b08c3774950064509706ef","pick":false,"score":55,"reason":"Borderline — remote role but lacks strong alignment with candidate's experience."},{"id":"6995144d81476f6176acf319","pick":false,"score":50,"reason":"Borderline — hybrid role conflicts with candidate's preference for remote work."},{"id":"69e932e84b0fa35a7076cbf4","pick":true,"score":70,"reason":"Strong fit — remote Senior Product Manager role with H1B sponsorship, aligns with candidate's seniority and experience."},{"id":"69e9bdc54b0fa35a7077018c","pick":false,"score":55,"reason":"Borderline — hybrid role conflicts with candidate's preference for remote work."}]},"t":"2026-04-23T12:38:46.458Z"}